README.md
setup.py
bin/__init__.py
bin/mkskl.py
wx_skeleton.egg-info/PKG-INFO
wx_skeleton.egg-info/SOURCES.txt
wx_skeleton.egg-info/dependency_links.txt
wx_skeleton.egg-info/entry_points.txt
wx_skeleton.egg-info/requires.txt
wx_skeleton.egg-info/top_level.txt
wxskeleton/.gitignore
wxskeleton/__init__.py
wxskeleton/skutils.py