Metadata-Version: 1.0
Name: wx-skeleton
Version: 0.2
Summary: Quickly build python project skeleton
Home-page: https://github.com/WangXin93/wx_skeleton
Author: Wang Xin
Author-email: wangxin19930411@163.com
License: BSD
Platform: UNKNOWN
